qhbayes/QHBayes.egg-info/PKG-INFO
qhbayes/QHBayes.egg-info/SOURCES.txt
qhbayes/QHBayes.egg-info/dependency_links.txt
qhbayes/QHBayes.egg-info/requires.txt
qhbayes/QHBayes.egg-info/top_level.txt
qhbayes/__init__.py
qhbayes/__main__.py
qhbayes/app/__init__.py
qhbayes/app/app.py
qhbayes/app/assets/VolcTools.css
qhbayes/app/assets/uob_logo.png
qhbayes/data/.~lock.MastinData.xlsx#
qhbayes/data/.~lock.SparksData.xlsx#
qhbayes/data/Aubry.py
qhbayes/data/AubryData.ods
qhbayes/data/AubryData.xlsx
qhbayes/data/IVESPA.py
qhbayes/data/IVESPAData.xlsx
qhbayes/data/IVESPAvn1.0.xlsx
qhbayes/data/Mastin.py
qhbayes/data/MastinData.xlsx
qhbayes/data/Sparks.py
qhbayes/data/SparksData.csv
qhbayes/data/SparksData.xlsx
qhbayes/data/__init__.py
qhbayes/gp/QHGP.py
qhbayes/gp/__init__.py
qhbayes/notebooks/.ipynb_checkpoints/qhbayes_example1-checkpoint.ipynb
qhbayes/notebooks/__init__.py
qhbayes/notebooks/notebook_tools.py
qhbayes/notebooks/qhbayes_example1.ipynb
qhbayes/notebooks/qhbayes_example2.ipynb
qhbayes/qhbayes.egg-info/PKG-INFO
qhbayes/qhbayes.egg-info/SOURCES.txt
qhbayes/qhbayes.egg-info/dependency_links.txt
qhbayes/qhbayes.egg-info/requires.txt
qhbayes/qhbayes.egg-info/top_level.txt
qhbayes/scripts/__init__.py
qhbayes/scripts/example.py
qhbayes/scripts/run_app.py
qhbayes/scripts/run_qhbayes.py
qhbayes/stats/QHStats.py
qhbayes/stats/__init__.py
qhbayes/utilities/__init__.py
qhbayes/utilities/number_tools.py
qhbayes/utilities/plot_tools.py
qhbayes/utilities/queryreport.py
qhbayes/utilities/string_tools.py
qhbayes-0.0.13.dist-info/entry_points.txt
qhbayes-0.0.13.dist-info/LICENSE
qhbayes-0.0.13.dist-info/WHEEL
qhbayes-0.0.13.dist-info/METADATA
qhbayes-0.0.13.dist-info/RECORD
