Metadata-Version: 2.1
Name: qhbayes
Version: 0.0.13
Summary: Bayesian methods for inferring mass eruption rate for column height (or vice versa) for volcanic eruptions
Author: markwoodhouse
Author-email: mark.woodhouse@bristol.ac.uk
Requires-Python: >=3.8,<3.11
Classifier: Programming Language :: Python :: 3
Classifier: Programming Language :: Python :: 3.10
Classifier: Programming Language :: Python :: 3.8
Classifier: Programming Language :: Python :: 3.9
Requires-Dist: Pint (>=0.18)
Requires-Dist: argparse (>=1.4.0)
Requires-Dist: arviz (>=0.13.0)
Requires-Dist: click (>=4.0,<8)
Requires-Dist: dash (>=2.3.0)
Requires-Dist: dash-bootstrap-components (>=1.0.3)
Requires-Dist: matplotlib (>=3.5.1)
Requires-Dist: nbconvert (>=7.2.9)
Requires-Dist: numpy (>=1.24.2)
Requires-Dist: odfpy (>=1.4.1)
Requires-Dist: openpyxl (>=3.0.9)
Requires-Dist: pandas (>=1.4.1)
Requires-Dist: plotly (>=5.6.0)
Requires-Dist: pymc (>4)
Requires-Dist: scipy (>=1.8.0)
Requires-Dist: seaborn (>=0.11.2)
Requires-Dist: setuptools (>=60.10.0)
